{"info":{"year":"2024","version":"1","description":"Exported from roboflow.com","contributor":"","url":"https://public.roboflow.com/object-detection/undefined","date_created":"2024-05-08T15:52:42+00:00"},"licenses":[{"id":1,"url":"https://creativecommons.org/licenses/by/4.0/","name":"CC BY 4.0"}],"categories":[{"id":0,"name":"clickables","supercategory":"none"},{"id":1,"name":"clickable","supercategory":"clickables"}],"images":[{"id":0,"license":1,"file_name":"8_png.rf.189ea4de05cc98f3843a2d70f291248e.jpg","height":640,"width":640,"date_captured":"2024-05-08T15:52:42+00:00"},{"id":1,"license":1,"file_name":"screenshot3_jpg.rf.3ed892b6902eb4c0b1597ed11edab819.jpg","height":640,"width":640,"date_captured":"2024-05-08T15:52:42+00:00"}],"annotations":[{"segmentation":[[283,9,831,9,831,50,283,50]],"area":22468,"bbox":[283,9,548,41],"iscrowd":0,"id":1,"image_id":1,"category_id":null},{"segmentation":[[832,8,875,8,875,47,832,47]],"area":1677,"bbox":[832,8,43,39],"iscrowd":0,"id":2,"image_id":1,"category_id":null},{"segmentation":[[880,11,957,11,957,48,880,48]],"area":2849,"bbox":[880,11,77,37],"iscrowd":0,"id":3,"image_id":1,"category_id":null},{"segmentation":[[963,8,1091,8,1091,48,963,48]],"area":5120,"bbox":[963,8,128,40],"iscrowd":0,"id":4,"image_id":1,"category_id":null},{"segmentation":[[1099,8,1173,8,1173,45,1099,45]],"area":2738,"bbox":[1099,8,74,37],"iscrowd":0,"id":5,"image_id":1,"category_id":null},{"segmentation":[[1181,7,1265,7,1265,46,1181,46]],"area":3276,"bbox":[1181,7,84,39],"iscrowd":0,"id":6,"image_id":1,"category_id":null},{"segmentation":[[348,128,411,128,411,157,348,157]],"area":1827,"bbox":[348,128,63,29],"iscrowd":0,"id":7,"image_id":1,"category_id":null},{"segmentation":[[428,127,548,127,548,156,428,156]],"area":3480,"bbox":[428,127,120,29],"iscrowd":0,"id":8,"image_id":1,"category_id":null},{"segmentation":[[968,72,1102,72,1102,105,968,105]],"area":4422,"bbox":[968,72,134,33],"iscrowd":0,"id":9,"image_id":1,"category_id":null},{"segmentation":[[1044,110,1102,110,1102,128,1044,128]],"area":1044,"bbox":[1044,110,58,18],"iscrowd":0,"id":10,"image_id":1,"category_id":null},{"segmentation":[[21,352,312,352,312,767,21,767]],"area":120765,"bbox":[21,352,291,415],"iscrowd":0,"id":11,"image_id":1,"category_id":null},{"segmentation":[[332,352,626,352,626,766,332,766]],"area":121716,"bbox":[332,352,294,414],"iscrowd":0,"id":12,"image_id":1,"category_id":null},{"segmentation":[[651,350,941,350,941,765,651,765]],"area":120350,"bbox":[651,350,290,415],"iscrowd":0,"id":13,"image_id":1,"category_id":null},{"segmentation":[[966,349,1261,349,1261,767,966,767]],"area":123310,"bbox":[966,349,295,418],"iscrowd":0,"id":14,"image_id":1,"category_id":null},{"segmentation":[[231,10,281,10,281,47,231,47]],"area":1850,"bbox":[231,10,50,37],"iscrowd":0,"id":15,"image_id":1,"category_id":null},{"segmentation":[[283,9,831,9,831,50,283,50]],"area":22468,"bbox":[283,9,548,41],"iscrowd":0,"id":16,"image_id":2,"category_id":null},{"segmentation":[[832,8,875,8,875,47,832,47]],"area":1677,"bbox":[832,8,43,39],"iscrowd":0,"id":17,"image_id":2,"category_id":null},{"segmentation":[[880,11,957,11,957,48,880,48]],"area":2849,"bbox":[880,11,77,37],"iscrowd":0,"id":18,"image_id":2,"category_id":null},{"segmentation":[[963,8,1091,8,1091,48,963,48]],"area":5120,"bbox":[963,8,128,40],"iscrowd":0,"id":19,"image_id":2,"category_id":null},{"segmentation":[[1099,8,1173,8,1173,45,1099,45]],"area":2738,"bbox":[1099,8,74,37],"iscrowd":0,"id":20,"image_id":2,"category_id":null},{"segmentation":[[1181,7,1265,7,1265,46,1181,46]],"area":3276,"bbox":[1181,7,84,39],"iscrowd":0,"id":21,"image_id":2,"category_id":null},{"segmentation":[[348,128,411,128,411,157,348,157]],"area":1827,"bbox":[348,128,63,29],"iscrowd":0,"id":22,"image_id":2,"category_id":null},{"segmentation":[[428,127,548,127,548,156,428,156]],"area":3480,"bbox":[428,127,120,29],"iscrowd":0,"id":23,"image_id":2,"category_id":null},{"segmentation":[[968,72,1102,72,1102,105,968,105]],"area":4422,"bbox":[968,72,134,33],"iscrowd":0,"id":24,"image_id":2,"category_id":null},{"segmentation":[[1044,110,1102,110,1102,128,1044,128]],"area":1044,"bbox":[1044,110,58,18],"iscrowd":0,"id":25,"image_id":2,"category_id":null},{"segmentation":[[231,10,281,10,281,47,231,47]],"area":1850,"bbox":[231,10,50,37],"iscrowd":0,"id":26,"image_id":2,"category_id":null},{"segmentation":[[650,101,786,101,786,142,650,142]],"area":5576,"bbox":[650,101,136,41],"iscrowd":0,"id":27,"image_id":2,"category_id":null},{"segmentation":[[790,100,906,100,906,141,790,141]],"area":4756,"bbox":[790,100,116,41],"iscrowd":0,"id":28,"image_id":2,"category_id":null},{"segmentation":[[479,543,609,543,609,580,479,580]],"area":4810,"bbox":[479,543,130,37],"iscrowd":0,"id":29,"image_id":2,"category_id":null},{"segmentation":[[572,100,642,100,642,141,572,141]],"area":2870,"bbox":[572,100,70,41],"iscrowd":0,"id":30,"image_id":2,"category_id":null},{"segmentation":[[8,147,125,147,125,188,8,188]],"area":4797,"bbox":[8,147,117,41],"iscrowd":0,"id":31,"image_id":2,"category_id":null},{"segmentation":[[8,195,172,195,172,231,8,231]],"area":5904,"bbox":[8,195,164,36],"iscrowd":0,"id":32,"image_id":2,"category_id":null},{"segmentation":[[16,237,180,237,180,273,16,273]],"area":5904,"bbox":[16,237,164,36],"iscrowd":0,"id":33,"image_id":2,"category_id":null},{"segmentation":[[28,279,192,279,192,315,28,315]],"area":5904,"bbox":[28,279,164,36],"iscrowd":0,"id":34,"image_id":2,"category_id":null},{"segmentation":[[25,317,189,317,189,344,25,344]],"area":4428,"bbox":[25,317,164,27],"iscrowd":0,"id":35,"image_id":2,"category_id":null},{"segmentation":[[25,343,189,343,189,370,25,370]],"area":4428,"bbox":[25,343,164,27],"iscrowd":0,"id":36,"image_id":2,"category_id":null},{"segmentation":[[22,369,186,369,186,389,22,389]],"area":3280,"bbox":[22,369,164,20],"iscrowd":0,"id":37,"image_id":2,"category_id":null},{"segmentation":[[22,394,186,394,186,414,22,414]],"area":3280,"bbox":[22,394,164,20],"iscrowd":0,"id":38,"image_id":2,"category_id":null},{"segmentation":[[13,456,177,456,177,476,13,476]],"area":3280,"bbox":[13,456,164,20],"iscrowd":0,"id":39,"image_id":2,"category_id":null},{"segmentation":[[12,521,176,521,176,541,12,541]],"area":3280,"bbox":[12,521,164,20],"iscrowd":0,"id":40,"image_id":2,"category_id":null},{"segmentation":[[11,585,175,585,175,605,11,605]],"area":3280,"bbox":[11,585,164,20],"iscrowd":0,"id":41,"image_id":2,"category_id":null},{"segmentation":[[621,543,702,543,702,577,621,577]],"area":2754,"bbox":[621,543,81,34],"iscrowd":0,"id":42,"image_id":2,"category_id":null},{"segmentation":[[859,545,1009,545,1009,577,859,577]],"area":4800,"bbox":[859,545,150,32],"iscrowd":0,"id":43,"image_id":2,"category_id":null},{"segmentation":[[791,544,852,544,852,575,791,575]],"area":1891,"bbox":[791,544,61,31],"iscrowd":0,"id":44,"image_id":2,"category_id":null},{"segmentation":[[716,543,777,543,777,574,716,574]],"area":1891,"bbox":[716,543,61,31],"iscrowd":0,"id":45,"image_id":2,"category_id":null},{"segmentation":[[6,65,63,65,63,92,6,92]],"area":1539,"bbox":[6,65,57,27],"iscrowd":0,"id":46,"image_id":2,"category_id":null},{"segmentation":[[283,9,831,9,831,50,283,50]],"area":22468,"bbox":[283,9,548,41],"iscrowd":0,"id":47,"image_id":3,"category_id":null},{"segmentation":[[832,8,875,8,875,47,832,47]],"area":1677,"bbox":[832,8,43,39],"iscrowd":0,"id":48,"image_id":3,"category_id":null},{"segmentation":[[880,11,957,11,957,48,880,48]],"area":2849,"bbox":[880,11,77,37],"iscrowd":0,"id":49,"image_id":3,"category_id":null},{"segmentation":[[963,8,1091,8,1091,48,963,48]],"area":5120,"bbox":[963,8,128,40],"iscrowd":0,"id":50,"image_id":3,"category_id":null},{"segmentation":[[1099,8,1173,8,1173,45,1099,45]],"area":2738,"bbox":[1099,8,74,37],"iscrowd":0,"id":51,"image_id":3,"category_id":null},{"segmentation":[[1181,7,1265,7,1265,46,1181,46]],"area":3276,"bbox":[1181,7,84,39],"iscrowd":0,"id":52,"image_id":3,"category_id":null},{"segmentation":[[348,128,411,128,411,157,348,157]],"area":1827,"bbox":[348,128,63,29],"iscrowd":0,"id":53,"image_id":3,"category_id":null},{"segmentation":[[428,127,548,127,548,156,428,156]],"area":3480,"bbox":[428,127,120,29],"iscrowd":0,"id":54,"image_id":3,"category_id":null},{"segmentation":[[968,72,1102,72,1102,105,968,105]],"area":4422,"bbox":[968,72,134,33],"iscrowd":0,"id":55,"image_id":3,"category_id":null},{"segmentation":[[1044,110,1102,110,1102,128,1044,128]],"area":1044,"bbox":[1044,110,58,18],"iscrowd":0,"id":56,"image_id":3,"category_id":null},{"segmentation":[[231,10,281,10,281,47,231,47]],"area":1850,"bbox":[231,10,50,37],"iscrowd":0,"id":57,"image_id":3,"category_id":null},{"segmentation":[[573,101,658,101,658,130,573,130]],"area":2465,"bbox":[573,101,85,29],"iscrowd":0,"id":58,"image_id":3,"category_id":null},{"segmentation":[[495,207,585,207,585,342,495,342]],"area":12150,"bbox":[495,207,90,135],"iscrowd":0,"id":59,"image_id":3,"category_id":null},{"segmentation":[[72,206,162,206,162,324,72,324]],"area":10620,"bbox":[72,206,90,118],"iscrowd":0,"id":60,"image_id":3,"category_id":null},{"segmentation":[[174,206,264,206,264,341,174,341]],"area":12150,"bbox":[174,206,90,135],"iscrowd":0,"id":61,"image_id":3,"category_id":null},{"segmentation":[[599,208,689,208,689,343,599,343]],"area":12150,"bbox":[599,208,90,135],"iscrowd":0,"id":62,"image_id":3,"category_id":null},{"segmentation":[[391,202,481,202,481,324,391,324]],"area":10980,"bbox":[391,202,90,122],"iscrowd":0,"id":63,"image_id":3,"category_id":null},{"segmentation":[[280,208,370,208,370,343,280,343]],"area":12150,"bbox":[280,208,90,135],"iscrowd":0,"id":64,"image_id":3,"category_id":null},{"segmentation":[[1129,206,1219,206,1219,328,1129,328]],"area":10980,"bbox":[1129,206,90,122],"iscrowd":0,"id":65,"image_id":3,"category_id":null},{"segmentation":[[1027,202,1117,202,1117,324,1027,324]],"area":10980,"bbox":[1027,202,90,122],"iscrowd":0,"id":66,"image_id":3,"category_id":null},{"segmentation":[[920,205,1010,205,1010,327,920,327]],"area":10980,"bbox":[920,205,90,122],"iscrowd":0,"id":67,"image_id":3,"category_id":null},{"segmentation":[[589,400,937,400,937,736,589,736]],"area":116928,"bbox":[589,400,348,336],"iscrowd":0,"id":68,"image_id":3,"category_id":null},{"segmentation":[[812,206,902,206,902,328,812,328]],"area":10980,"bbox":[812,206,90,122],"iscrowd":0,"id":69,"image_id":3,"category_id":null},{"segmentation":[[240,402,588,402,588,738,240,738]],"area":116928,"bbox":[240,402,348,336],"iscrowd":0,"id":70,"image_id":3,"category_id":null},{"segmentation":[[589,400,937,400,937,736,589,736]],"area":116928,"bbox":[589,400,348,336],"iscrowd":0,"id":71,"image_id":3,"category_id":null},{"segmentation":[[941,399,1276,399,1276,735,941,735]],"area":112560,"bbox":[941,399,335,336],"iscrowd":0,"id":72,"image_id":3,"category_id":null},{"segmentation":[[1226,249,1262,249,1262,286,1226,286]],"area":1332,"bbox":[1226,249,36,37],"iscrowd":0,"id":73,"image_id":3,"category_id":null},{"segmentation":[[19,247,55,247,55,284,19,284]],"area":1332,"bbox":[19,247,36,37],"iscrowd":0,"id":74,"image_id":3,"category_id":null},{"segmentation":[[19,247,55,247,55,284,19,284]],"area":1332,"bbox":[19,247,36,37],"iscrowd":0,"id":75,"image_id":3,"category_id":null},{"segmentation":[[705,208,795,208,795,330,705,330]],"area":10980,"bbox":[705,208,90,122],"iscrowd":0,"id":76,"image_id":3,"category_id":null},{"segmentation":[[19,779,205,779,205,799,19,799]],"area":3720,"bbox":[19,779,186,20],"iscrowd":0,"id":77,"image_id":3,"category_id":null},{"segmentation":[[13,425,92,425,92,445,13,445]],"area":1580,"bbox":[13,425,79,20],"iscrowd":0,"id":78,"image_id":3,"category_id":null},{"segmentation":[[13,448,92,448,92,468,13,468]],"area":1580,"bbox":[13,448,79,20],"iscrowd":0,"id":79,"image_id":3,"category_id":null},{"segmentation":[[13,466,92,466,92,486,13,486]],"area":1580,"bbox":[13,466,79,20],"iscrowd":0,"id":80,"image_id":3,"category_id":null},{"segmentation":[[13,488,92,488,92,508,13,508]],"area":1580,"bbox":[13,488,79,20],"iscrowd":0,"id":81,"image_id":3,"category_id":null},{"segmentation":[[19,555,98,555,98,575,19,575]],"area":1580,"bbox":[19,555,79,20],"iscrowd":0,"id":82,"image_id":3,"category_id":null},{"segmentation":[[19,577,205,577,205,597,19,597]],"area":3720,"bbox":[19,577,186,20],"iscrowd":0,"id":83,"image_id":3,"category_id":null},{"segmentation":[[19,601,205,601,205,621,19,621]],"area":3720,"bbox":[19,601,186,20],"iscrowd":0,"id":84,"image_id":3,"category_id":null},{"segmentation":[[19,689,205,689,205,709,19,709]],"area":3720,"bbox":[19,689,186,20],"iscrowd":0,"id":85,"image_id":3,"category_id":null},{"segmentation":[[19,712,205,712,205,732,19,732]],"area":3720,"bbox":[19,712,186,20],"iscrowd":0,"id":86,"image_id":3,"category_id":null},{"segmentation":[[19,735,205,735,205,755,19,755]],"area":3720,"bbox":[19,735,186,20],"iscrowd":0,"id":87,"image_id":3,"category_id":null},{"segmentation":[[19,756,205,756,205,776,19,776]],"area":3720,"bbox":[19,756,186,20],"iscrowd":0,"id":88,"image_id":3,"category_id":null},{"segmentation":[[20,68,65,68,65,94,20,94]],"area":1170,"bbox":[20,68,45,26],"iscrowd":0,"id":89,"image_id":3,"category_id":null},{"segmentation":[[283,9,831,9,831,50,283,50]],"area":22468,"bbox":[283,9,548,41],"iscrowd":0,"id":90,"image_id":4,"category_id":null},{"segmentation":[[832,8,875,8,875,47,832,47]],"area":1677,"bbox":[832,8,43,39],"iscrowd":0,"id":91,"image_id":4,"category_id":null},{"segmentation":[[880,11,957,11,957,48,880,48]],"area":2849,"bbox":[880,11,77,37],"iscrowd":0,"id":92,"image_id":4,"category_id":null},{"segmentation":[[963,8,1091,8,1091,48,963,48]],"area":5120,"bbox":[963,8,128,40],"iscrowd":0,"id":93,"image_id":4,"category_id":null},{"segmentation":[[1099,8,1173,8,1173,45,1099,45]],"area":2738,"bbox":[1099,8,74,37],"iscrowd":0,"id":94,"image_id":4,"category_id":null},{"segmentation":[[1181,7,1265,7,1265,46,1181,46]],"area":3276,"bbox":[1181,7,84,39],"iscrowd":0,"id":95,"image_id":4,"category_id":null},{"segmentation":[[968,72,1102,72,1102,105,968,105]],"area":4422,"bbox":[968,72,134,33],"iscrowd":0,"id":96,"image_id":4,"category_id":null},{"segmentation":[[1044,110,1102,110,1102,128,1044,128]],"area":1044,"bbox":[1044,110,58,18],"iscrowd":0,"id":97,"image_id":4,"category_id":null},{"segmentation":[[231,10,281,10,281,47,231,47]],"area":1850,"bbox":[231,10,50,37],"iscrowd":0,"id":98,"image_id":4,"category_id":null},{"segmentation":[[460,66,491,66,491,95,460,95]],"area":899,"bbox":[460,66,31,29],"iscrowd":0,"id":99,"image_id":4,"category_id":null},{"segmentation":[[495,207,585,207,585,342,495,342]],"area":12150,"bbox":[495,207,90,135],"iscrowd":0,"id":100,"image_id":4,"category_id":null},{"segmentation":[[72,206,162,206,162,324,72,324]],"area":10620,"bbox":[72,206,90,118],"iscrowd":0,"id":101,"image_id":4,"category_id":null},{"segmentation":[[174,206,264,206,264,341,174,341]],"area":12150,"bbox":[174,206,90,135],"iscrowd":0,"id":102,"image_id":4,"category_id":null},{"segmentation":[[599,208,689,208,689,343,599,343]],"area":12150,"bbox":[599,208,90,135],"iscrowd":0,"id":103,"image_id":4,"category_id":null},{"segmentation":[[391,202,481,202,481,324,391,324]],"area":10980,"bbox":[391,202,90,122],"iscrowd":0,"id":104,"image_id":4,"category_id":null},{"segmentation":[[280,208,370,208,370,343,280,343]],"area":12150,"bbox":[280,208,90,135],"iscrowd":0,"id":105,"image_id":4,"category_id":null},{"segmentation":[[1129,206,1219,206,1219,328,1129,328]],"area":10980,"bbox":[1129,206,90,122],"iscrowd":0,"id":106,"image_id":4,"category_id":null},{"segmentation":[[1027,202,1117,202,1117,324,1027,324]],"area":10980,"bbox":[1027,202,90,122],"iscrowd":0,"id":107,"image_id":4,"category_id":null},{"segmentation":[[920,205,1010,205,1010,327,920,327]],"area":10980,"bbox":[920,205,90,122],"iscrowd":0,"id":108,"image_id":4,"category_id":null},{"segmentation":[[589,400,937,400,937,736,589,736]],"area":116928,"bbox":[589,400,348,336],"iscrowd":0,"id":109,"image_id":4,"category_id":null},{"segmentation":[[812,206,902,206,902,328,812,328]],"area":10980,"bbox":[812,206,90,122],"iscrowd":0,"id":110,"image_id":4,"category_id":null},{"segmentation":[[240,402,588,402,588,738,240,738]],"area":116928,"bbox":[240,402,348,336],"iscrowd":0,"id":111,"image_id":4,"category_id":null},{"segmentation":[[589,400,937,400,937,736,589,736]],"area":116928,"bbox":[589,400,348,336],"iscrowd":0,"id":112,"image_id":4,"category_id":null},{"segmentation":[[941,399,1276,399,1276,735,941,735]],"area":112560,"bbox":[941,399,335,336],"iscrowd":0,"id":113,"image_id":4,"category_id":null},{"segmentation":[[1226,249,1262,249,1262,286,1226,286]],"area":1332,"bbox":[1226,249,36,37],"iscrowd":0,"id":114,"image_id":4,"category_id":null},{"segmentation":[[19,247,55,247,55,284,19,284]],"area":1332,"bbox":[19,247,36,37],"iscrowd":0,"id":115,"image_id":4,"category_id":null},{"segmentation":[[19,247,55,247,55,284,19,284]],"area":1332,"bbox":[19,247,36,37],"iscrowd":0,"id":116,"image_id":4,"category_id":null},{"segmentation":[[705,208,795,208,795,330,705,330]],"area":10980,"bbox":[705,208,90,122],"iscrowd":0,"id":117,"image_id":4,"category_id":null},{"segmentation":[[19,779,205,779,205,799,19,799]],"area":3720,"bbox":[19,779,186,20],"iscrowd":0,"id":118,"image_id":4,"category_id":null},{"segmentation":[[13,425,92,425,92,445,13,445]],"area":1580,"bbox":[13,425,79,20],"iscrowd":0,"id":119,"image_id":4,"category_id":null},{"segmentation":[[13,448,92,448,92,468,13,468]],"area":1580,"bbox":[13,448,79,20],"iscrowd":0,"id":120,"image_id":4,"category_id":null},{"segmentation":[[13,466,92,466,92,486,13,486]],"area":1580,"bbox":[13,466,79,20],"iscrowd":0,"id":121,"image_id":4,"category_id":null},{"segmentation":[[13,488,92,488,92,508,13,508]],"area":1580,"bbox":[13,488,79,20],"iscrowd":0,"id":122,"image_id":4,"category_id":null},{"segmentation":[[19,555,98,555,98,575,19,575]],"area":1580,"bbox":[19,555,79,20],"iscrowd":0,"id":123,"image_id":4,"category_id":null},{"segmentation":[[19,577,205,577,205,597,19,597]],"area":3720,"bbox":[19,577,186,20],"iscrowd":0,"id":124,"image_id":4,"category_id":null},{"segmentation":[[19,601,205,601,205,621,19,621]],"area":3720,"bbox":[19,601,186,20],"iscrowd":0,"id":125,"image_id":4,"category_id":null},{"segmentation":[[19,689,205,689,205,709,19,709]],"area":3720,"bbox":[19,689,186,20],"iscrowd":0,"id":126,"image_id":4,"category_id":null},{"segmentation":[[19,712,205,712,205,732,19,732]],"area":3720,"bbox":[19,712,186,20],"iscrowd":0,"id":127,"image_id":4,"category_id":null},{"segmentation":[[19,735,205,735,205,755,19,755]],"area":3720,"bbox":[19,735,186,20],"iscrowd":0,"id":128,"image_id":4,"category_id":null},{"segmentation":[[19,756,205,756,205,776,19,776]],"area":3720,"bbox":[19,756,186,20],"iscrowd":0,"id":129,"image_id":4,"category_id":null},{"segmentation":[[573,101,658,101,658,130,573,130]],"area":2465,"bbox":[573,101,85,29],"iscrowd":0,"id":130,"image_id":4,"category_id":null},{"segmentation":[[442,101,559,101,559,130,442,130]],"area":3393,"bbox":[442,101,117,29],"iscrowd":0,"id":131,"image_id":4,"category_id":null},{"segmentation":[[354,101,439,101,439,130,354,130]],"area":2465,"bbox":[354,101,85,29],"iscrowd":0,"id":132,"image_id":4,"category_id":null},{"segmentation":[[297,101,347,101,347,130,297,130]],"area":1450,"bbox":[297,101,50,29],"iscrowd":0,"id":133,"image_id":4,"category_id":null},{"segmentation":[[192,101,290,101,290,130,192,130]],"area":2842,"bbox":[192,101,98,29],"iscrowd":0,"id":134,"image_id":4,"category_id":null},{"segmentation":[[123,101,183,101,183,130,123,130]],"area":1740,"bbox":[123,101,60,29],"iscrowd":0,"id":135,"image_id":4,"category_id":null},{"segmentation":[[23,101,108,101,108,130,23,130]],"area":2465,"bbox":[23,101,85,29],"iscrowd":0,"id":136,"image_id":4,"category_id":null},{"segmentation":[[15,67,72,67,72,93,15,93]],"area":1482,"bbox":[15,67,57,26],"iscrowd":0,"id":137,"image_id":4,"category_id":null},{"segmentation":[[180,66,296,66,296,95,180,95]],"area":3364,"bbox":[180,66,116,29],"iscrowd":0,"id":138,"image_id":4,"category_id":null},{"segmentation":[[308,66,370,66,370,95,308,95]],"area":1798,"bbox":[308,66,62,29],"iscrowd":0,"id":139,"image_id":4,"category_id":null},{"segmentation":[[374,66,459,66,459,95,374,95]],"area":2465,"bbox":[374,66,85,29],"iscrowd":0,"id":140,"image_id":4,"category_id":null},{"segmentation":[[80,69,165,69,165,95,80,95]],"area":2210,"bbox":[80,69,85,26],"iscrowd":0,"id":141,"image_id":4,"category_id":null},{"segmentation":[[80,69,165,69,165,95,80,95]],"area":2210,"bbox":[80,69,85,26],"iscrowd":0,"id":142,"image_id":4,"category_id":null},{"segmentation":[[283,9,831,9,831,50,283,50]],"area":22468,"bbox":[283,9,548,41],"iscrowd":0,"id":143,"image_id":5,"category_id":null},{"segmentation":[[832,8,875,8,875,47,832,47]],"area":1677,"bbox":[832,8,43,39],"iscrowd":0,"id":144,"image_id":5,"category_id":null},{"segmentation":[[880,11,957,11,957,48,880,48]],"area":2849,"bbox":[880,11,77,37],"iscrowd":0,"id":145,"image_id":5,"category_id":null},{"segmentation":[[963,8,1091,8,1091,48,963,48]],"area":5120,"bbox":[963,8,128,40],"iscrowd":0,"id":146,"image_id":5,"category_id":null},{"segmentation":[[1099,8,1173,8,1173,45,1099,45]],"area":2738,"bbox":[1099,8,74,37],"iscrowd":0,"id":147,"image_id":5,"category_id":null},{"segmentation":[[1181,7,1265,7,1265,46,1181,46]],"area":3276,"bbox":[1181,7,84,39],"iscrowd":0,"id":148,"image_id":5,"category_id":null},{"segmentation":[[348,128,411,128,411,157,348,157]],"area":1827,"bbox":[348,128,63,29],"iscrowd":0,"id":149,"image_id":5,"category_id":null},{"segmentation":[[428,127,548,127,548,156,428,156]],"area":3480,"bbox":[428,127,120,29],"iscrowd":0,"id":150,"image_id":5,"category_id":null},{"segmentation":[[968,72,1102,72,1102,105,968,105]],"area":4422,"bbox":[968,72,134,33],"iscrowd":0,"id":151,"image_id":5,"category_id":null},{"segmentation":[[1044,110,1102,110,1102,128,1044,128]],"area":1044,"bbox":[1044,110,58,18],"iscrowd":0,"id":152,"image_id":5,"category_id":null},{"segmentation":[[231,10,281,10,281,47,231,47]],"area":1850,"bbox":[231,10,50,37],"iscrowd":0,"id":153,"image_id":5,"category_id":null},{"segmentation":[[573,101,658,101,658,130,573,130]],"area":2465,"bbox":[573,101,85,29],"iscrowd":0,"id":154,"image_id":5,"category_id":null},{"segmentation":[[495,207,585,207,585,342,495,342]],"area":12150,"bbox":[495,207,90,135],"iscrowd":0,"id":155,"image_id":5,"category_id":null},{"segmentation":[[72,206,162,206,162,324,72,324]],"area":10620,"bbox":[72,206,90,118],"iscrowd":0,"id":156,"image_id":5,"category_id":null},{"segmentation":[[174,206,264,206,264,341,174,341]],"area":12150,"bbox":[174,206,90,135],"iscrowd":0,"id":157,"image_id":5,"category_id":null},{"segmentation":[[599,208,689,208,689,343,599,343]],"area":12150,"bbox":[599,208,90,135],"iscrowd":0,"id":158,"image_id":5,"category_id":null},{"segmentation":[[391,202,481,202,481,324,391,324]],"area":10980,"bbox":[391,202,90,122],"iscrowd":0,"id":159,"image_id":5,"category_id":null},{"segmentation":[[280,208,370,208,370,343,280,343]],"area":12150,"bbox":[280,208,90,135],"iscrowd":0,"id":160,"image_id":5,"category_id":null},{"segmentation":[[1129,206,1219,206,1219,328,1129,328]],"area":10980,"bbox":[1129,206,90,122],"iscrowd":0,"id":161,"image_id":5,"category_id":null},{"segmentation":[[1027,202,1117,202,1117,324,1027,324]],"area":10980,"bbox":[1027,202,90,122],"iscrowd":0,"id":162,"image_id":5,"category_id":null},{"segmentation":[[920,205,1010,205,1010,327,920,327]],"area":10980,"bbox":[920,205,90,122],"iscrowd":0,"id":163,"image_id":5,"category_id":null},{"segmentation":[[589,400,937,400,937,736,589,736]],"area":116928,"bbox":[589,400,348,336],"iscrowd":0,"id":164,"image_id":5,"category_id":null},{"segmentation":[[812,206,902,206,902,328,812,328]],"area":10980,"bbox":[812,206,90,122],"iscrowd":0,"id":165,"image_id":5,"category_id":null},{"segmentation":[[240,402,588,402,588,738,240,738]],"area":116928,"bbox":[240,402,348,336],"iscrowd":0,"id":166,"image_id":5,"category_id":null},{"segmentation":[[589,400,937,400,937,736,589,736]],"area":116928,"bbox":[589,400,348,336],"iscrowd":0,"id":167,"image_id":5,"category_id":null},{"segmentation":[[941,399,1276,399,1276,735,941,735]],"area":112560,"bbox":[941,399,335,336],"iscrowd":0,"id":168,"image_id":5,"category_id":null},{"segmentation":[[1226,249,1262,249,1262,286,1226,286]],"area":1332,"bbox":[1226,249,36,37],"iscrowd":0,"id":169,"image_id":5,"category_id":null},{"segmentation":[[19,247,55,247,55,284,19,284]],"area":1332,"bbox":[19,247,36,37],"iscrowd":0,"id":170,"image_id":5,"category_id":null},{"segmentation":[[19,247,55,247,55,284,19,284]],"area":1332,"bbox":[19,247,36,37],"iscrowd":0,"id":171,"image_id":5,"category_id":null},{"segmentation":[[705,208,795,208,795,330,705,330]],"area":10980,"bbox":[705,208,90,122],"iscrowd":0,"id":172,"image_id":5,"category_id":null},{"segmentation":[[19,779,205,779,205,799,19,799]],"area":3720,"bbox":[19,779,186,20],"iscrowd":0,"id":173,"image_id":5,"category_id":null},{"segmentation":[[13,425,92,425,92,445,13,445]],"area":1580,"bbox":[13,425,79,20],"iscrowd":0,"id":174,"image_id":5,"category_id":null},{"segmentation":[[13,448,92,448,92,468,13,468]],"area":1580,"bbox":[13,448,79,20],"iscrowd":0,"id":175,"image_id":5,"category_id":null},{"segmentation":[[13,466,92,466,92,486,13,486]],"area":1580,"bbox":[13,466,79,20],"iscrowd":0,"id":176,"image_id":5,"category_id":null},{"segmentation":[[13,488,92,488,92,508,13,508]],"area":1580,"bbox":[13,488,79,20],"iscrowd":0,"id":177,"image_id":5,"category_id":null},{"segmentation":[[19,555,98,555,98,575,19,575]],"area":1580,"bbox":[19,555,79,20],"iscrowd":0,"id":178,"image_id":5,"category_id":null},{"segmentation":[[19,577,205,577,205,597,19,597]],"area":3720,"bbox":[19,577,186,20],"iscrowd":0,"id":179,"image_id":5,"category_id":null},{"segmentation":[[19,601,205,601,205,621,19,621]],"area":3720,"bbox":[19,601,186,20],"iscrowd":0,"id":180,"image_id":5,"category_id":null},{"segmentation":[[19,689,205,689,205,709,19,709]],"area":3720,"bbox":[19,689,186,20],"iscrowd":0,"id":181,"image_id":5,"category_id":null},{"segmentation":[[19,712,205,712,205,732,19,732]],"area":3720,"bbox":[19,712,186,20],"iscrowd":0,"id":182,"image_id":5,"category_id":null},{"segmentation":[[19,735,205,735,205,755,19,755]],"area":3720,"bbox":[19,735,186,20],"iscrowd":0,"id":183,"image_id":5,"category_id":null},{"segmentation":[[19,756,205,756,205,776,19,776]],"area":3720,"bbox":[19,756,186,20],"iscrowd":0,"id":184,"image_id":5,"category_id":null},{"segmentation":[[20,68,65,68,65,94,20,94]],"area":1170,"bbox":[20,68,45,26],"iscrowd":0,"id":185,"image_id":5,"category_id":null},{"segmentation":[[367,9,831,9,831,50,367,50]],"area":19024,"bbox":[367,9,464,41],"iscrowd":0,"id":186,"image_id":6,"category_id":null},{"segmentation":[[832,8,875,8,875,47,832,47]],"area":1677,"bbox":[832,8,43,39],"iscrowd":0,"id":187,"image_id":6,"category_id":null},{"segmentation":[[880,11,957,11,957,48,880,48]],"area":2849,"bbox":[880,11,77,37],"iscrowd":0,"id":188,"image_id":6,"category_id":null},{"segmentation":[[963,8,1091,8,1091,48,963,48]],"area":5120,"bbox":[963,8,128,40],"iscrowd":0,"id":189,"image_id":6,"category_id":null},{"segmentation":[[1099,8,1173,8,1173,45,1099,45]],"area":2738,"bbox":[1099,8,74,37],"iscrowd":0,"id":190,"image_id":6,"category_id":null},{"segmentation":[[1181,7,1265,7,1265,46,1181,46]],"area":3276,"bbox":[1181,7,84,39],"iscrowd":0,"id":191,"image_id":6,"category_id":null},{"segmentation":[[968,72,1102,72,1102,105,968,105]],"area":4422,"bbox":[968,72,134,33],"iscrowd":0,"id":192,"image_id":6,"category_id":null},{"segmentation":[[1044,110,1102,110,1102,128,1044,128]],"area":1044,"bbox":[1044,110,58,18],"iscrowd":0,"id":193,"image_id":6,"category_id":null},{"segmentation":[[231,10,368,10,368,47,231,47]],"area":5069,"bbox":[231,10,137,37],"iscrowd":0,"id":194,"image_id":6,"category_id":null},{"segmentation":[[254,462,443,462,443,766,254,766]],"area":57456,"bbox":[254,462,189,304],"iscrowd":0,"id":195,"image_id":6,"category_id":null},{"segmentation":[[446,461,635,461,635,765,446,765]],"area":57456,"bbox":[446,461,189,304],"iscrowd":0,"id":196,"image_id":6,"category_id":null},{"segmentation":[[640,461,829,461,829,765,640,765]],"area":57456,"bbox":[640,461,189,304],"iscrowd":0,"id":197,"image_id":6,"category_id":null},{"segmentation":[[835,462,1024,462,1024,766,835,766]],"area":57456,"bbox":[835,462,189,304],"iscrowd":0,"id":198,"image_id":6,"category_id":null},{"segmentation":[[1027,462,1216,462,1216,766,1027,766]],"area":57456,"bbox":[1027,462,189,304],"iscrowd":0,"id":199,"image_id":6,"category_id":null},{"segmentation":[[62,461,251,461,251,765,62,765]],"area":57456,"bbox":[62,461,189,304],"iscrowd":0,"id":200,"image_id":6,"category_id":null},{"segmentation":[[19,587,53,587,53,626,19,626]],"area":1326,"bbox":[19,587,34,39],"iscrowd":0,"id":201,"image_id":6,"category_id":null},{"segmentation":[[1226,584,1260,584,1260,623,1226,623]],"area":1326,"bbox":[1226,584,34,39],"iscrowd":0,"id":202,"image_id":6,"category_id":null},{"segmentation":[[568,103,666,103,666,132,568,132]],"area":2842,"bbox":[568,103,98,29],"iscrowd":0,"id":203,"image_id":6,"category_id":null},{"segmentation":[[13,65,70,65,70,94,13,94]],"area":1653,"bbox":[13,65,57,29],"iscrowd":0,"id":204,"image_id":6,"category_id":null},{"segmentation":[[76,65,169,65,169,94,76,94]],"area":2697,"bbox":[76,65,93,29],"iscrowd":0,"id":205,"image_id":6,"category_id":null},{"segmentation":[[173,64,302,64,302,93,173,93]],"area":3741,"bbox":[173,64,129,29],"iscrowd":0,"id":206,"image_id":6,"category_id":null},{"segmentation":[[308,64,365,64,365,93,308,93]],"area":1653,"bbox":[308,64,57,29],"iscrowd":0,"id":207,"image_id":6,"category_id":null},{"segmentation":[[370,65,452,65,452,94,370,94]],"area":2378,"bbox":[370,65,82,29],"iscrowd":0,"id":208,"image_id":6,"category_id":null},{"segmentation":[[460,60,497,60,497,92,460,92]],"area":1184,"bbox":[460,60,37,32],"iscrowd":0,"id":209,"image_id":6,"category_id":null},{"segmentation":[[13,103,112,103,112,132,13,132]],"area":2871,"bbox":[13,103,99,29],"iscrowd":0,"id":210,"image_id":6,"category_id":null},{"segmentation":[[115,103,193,103,193,132,115,132]],"area":2262,"bbox":[115,103,78,29],"iscrowd":0,"id":211,"image_id":6,"category_id":null},{"segmentation":[[197,103,292,103,292,132,197,132]],"area":2755,"bbox":[197,103,95,29],"iscrowd":0,"id":212,"image_id":6,"category_id":null},{"segmentation":[[296,103,352,103,352,132,296,132]],"area":1624,"bbox":[296,103,56,29],"iscrowd":0,"id":213,"image_id":6,"category_id":null},{"segmentation":[[352,103,432,103,432,132,352,132]],"area":2320,"bbox":[352,103,80,29],"iscrowd":0,"id":214,"image_id":6,"category_id":null},{"segmentation":[[435,103,564,103,564,132,435,132]],"area":3741,"bbox":[435,103,129,29],"iscrowd":0,"id":215,"image_id":6,"category_id":null},{"segmentation":[[406,9,831,9,831,50,406,50]],"area":17425,"bbox":[406,9,425,41],"iscrowd":0,"id":216,"image_id":7,"category_id":null},{"segmentation":[[832,8,875,8,875,47,832,47]],"area":1677,"bbox":[832,8,43,39],"iscrowd":0,"id":217,"image_id":7,"category_id":null},{"segmentation":[[880,11,957,11,957,48,880,48]],"area":2849,"bbox":[880,11,77,37],"iscrowd":0,"id":218,"image_id":7,"category_id":null},{"segmentation":[[963,8,1091,8,1091,48,963,48]],"area":5120,"bbox":[963,8,128,40],"iscrowd":0,"id":219,"image_id":7,"category_id":null},{"segmentation":[[1099,8,1173,8,1173,45,1099,45]],"area":2738,"bbox":[1099,8,74,37],"iscrowd":0,"id":220,"image_id":7,"category_id":null},{"segmentation":[[1181,7,1265,7,1265,46,1181,46]],"area":3276,"bbox":[1181,7,84,39],"iscrowd":0,"id":221,"image_id":7,"category_id":null},{"segmentation":[[348,128,411,128,411,157,348,157]],"area":1827,"bbox":[348,128,63,29],"iscrowd":0,"id":222,"image_id":7,"category_id":null},{"segmentation":[[428,127,548,127,548,156,428,156]],"area":3480,"bbox":[428,127,120,29],"iscrowd":0,"id":223,"image_id":7,"category_id":null},{"segmentation":[[968,72,1102,72,1102,105,968,105]],"area":4422,"bbox":[968,72,134,33],"iscrowd":0,"id":224,"image_id":7,"category_id":null},{"segmentation":[[1044,110,1102,110,1102,128,1044,128]],"area":1044,"bbox":[1044,110,58,18],"iscrowd":0,"id":225,"image_id":7,"category_id":null},{"segmentation":[[231,10,409,10,409,47,231,47]],"area":6586,"bbox":[231,10,178,37],"iscrowd":0,"id":226,"image_id":7,"category_id":null},{"segmentation":[[16,177,236,177,236,236,16,236]],"area":12980,"bbox":[16,177,220,59],"iscrowd":0,"id":227,"image_id":7,"category_id":null},{"segmentation":[[38,662,255,662,255,691,38,691]],"area":6293,"bbox":[38,662,217,29],"iscrowd":0,"id":228,"image_id":7,"category_id":null},{"segmentation":[[35,618,242,618,242,640,35,640]],"area":4554,"bbox":[35,618,207,22],"iscrowd":0,"id":229,"image_id":7,"category_id":null},{"segmentation":[[38,575,255,575,255,597,38,597]],"area":4774,"bbox":[38,575,217,22],"iscrowd":0,"id":230,"image_id":7,"category_id":null},{"segmentation":[[35,597,252,597,252,619,35,619]],"area":4774,"bbox":[35,597,217,22],"iscrowd":0,"id":231,"image_id":7,"category_id":null},{"segmentation":[[18,237,235,237,235,259,18,259]],"area":4774,"bbox":[18,237,217,22],"iscrowd":0,"id":232,"image_id":7,"category_id":null},{"segmentation":[[39,559,256,559,256,575,39,575]],"area":3472,"bbox":[39,559,217,16],"iscrowd":0,"id":233,"image_id":7,"category_id":null},{"segmentation":[[38,523,245,523,245,538,38,538]],"area":3105,"bbox":[38,523,207,15],"iscrowd":0,"id":234,"image_id":7,"category_id":null},{"segmentation":[[18,237,235,237,235,259,18,259]],"area":4774,"bbox":[18,237,217,22],"iscrowd":0,"id":235,"image_id":7,"category_id":null},{"segmentation":[[16,259,233,259,233,281,16,281]],"area":4774,"bbox":[16,259,217,22],"iscrowd":0,"id":236,"image_id":7,"category_id":null},{"segmentation":[[31,360,238,360,238,382,31,382]],"area":4554,"bbox":[31,360,207,22],"iscrowd":0,"id":237,"image_id":7,"category_id":null},{"segmentation":[[34,317,251,317,251,339,34,339]],"area":4774,"bbox":[34,317,217,22],"iscrowd":0,"id":238,"image_id":7,"category_id":null},{"segmentation":[[31,339,248,339,248,361,31,361]],"area":4774,"bbox":[31,339,217,22],"iscrowd":0,"id":239,"image_id":7,"category_id":null},{"segmentation":[[35,295,252,295,252,317,35,317]],"area":4774,"bbox":[35,295,217,22],"iscrowd":0,"id":240,"image_id":7,"category_id":null},{"segmentation":[[30,279,237,279,237,301,30,301]],"area":4554,"bbox":[30,279,207,22],"iscrowd":0,"id":241,"image_id":7,"category_id":null},{"segmentation":[[36,500,253,500,253,522,36,522]],"area":4774,"bbox":[36,500,217,22],"iscrowd":0,"id":242,"image_id":7,"category_id":null},{"segmentation":[[33,484,240,484,240,506,33,506]],"area":4554,"bbox":[33,484,207,22],"iscrowd":0,"id":243,"image_id":7,"category_id":null},{"segmentation":[[36,441,253,441,253,463,36,463]],"area":4774,"bbox":[36,441,217,22],"iscrowd":0,"id":244,"image_id":7,"category_id":null},{"segmentation":[[33,463,250,463,250,485,33,485]],"area":4774,"bbox":[33,463,217,22],"iscrowd":0,"id":245,"image_id":7,"category_id":null},{"segmentation":[[37,419,254,419,254,441,37,441]],"area":4774,"bbox":[37,419,217,22],"iscrowd":0,"id":246,"image_id":7,"category_id":null},{"segmentation":[[32,403,239,403,239,425,32,425]],"area":4554,"bbox":[32,403,207,22],"iscrowd":0,"id":247,"image_id":7,"category_id":null},{"segmentation":[[34,376,251,376,251,398,34,398]],"area":4774,"bbox":[34,376,217,22],"iscrowd":0,"id":248,"image_id":7,"category_id":null},{"segmentation":[[38,541,245,541,245,556,38,556]],"area":3105,"bbox":[38,541,207,15],"iscrowd":0,"id":249,"image_id":7,"category_id":null},{"segmentation":[[38,541,245,541,245,556,38,556]],"area":3105,"bbox":[38,541,207,15],"iscrowd":0,"id":250,"image_id":7,"category_id":null},{"segmentation":[[38,639,255,639,255,661,38,661]],"area":4774,"bbox":[38,639,217,22],"iscrowd":0,"id":251,"image_id":7,"category_id":null},{"segmentation":[[38,639,255,639,255,661,38,661]],"area":4774,"bbox":[38,639,217,22],"iscrowd":0,"id":252,"image_id":7,"category_id":null},{"segmentation":[[37,695,221,695,221,717,37,717]],"area":4048,"bbox":[37,695,184,22],"iscrowd":0,"id":253,"image_id":7,"category_id":null},{"segmentation":[[273,209,507,209,507,754,273,754]],"area":127530,"bbox":[273,209,234,545],"iscrowd":0,"id":254,"image_id":7,"category_id":null},{"segmentation":[[522,211,749,211,749,763,522,763]],"area":125304,"bbox":[522,211,227,552],"iscrowd":0,"id":255,"image_id":7,"category_id":null},{"segmentation":[[758,208,1007,208,1007,768,758,768]],"area":139440,"bbox":[758,208,249,560],"iscrowd":0,"id":256,"image_id":7,"category_id":null},{"segmentation":[[1018,211,1259,211,1259,773,1018,773]],"area":135442,"bbox":[1018,211,241,562],"iscrowd":0,"id":257,"image_id":7,"category_id":null},{"segmentation":[[5,60,70,60,70,96,5,96]],"area":2340,"bbox":[5,60,65,36],"iscrowd":0,"id":258,"image_id":7,"category_id":null},{"segmentation":[[283,9,831,9,831,50,283,50]],"area":22468,"bbox":[283,9,548,41],"iscrowd":0,"id":259,"image_id":8,"category_id":null},{"segmentation":[[832,8,875,8,875,47,832,47]],"area":1677,"bbox":[832,8,43,39],"iscrowd":0,"id":260,"image_id":8,"category_id":null},{"segmentation":[[880,11,957,11,957,48,880,48]],"area":2849,"bbox":[880,11,77,37],"iscrowd":0,"id":261,"image_id":8,"category_id":null},{"segmentation":[[963,8,1091,8,1091,48,963,48]],"area":5120,"bbox":[963,8,128,40],"iscrowd":0,"id":262,"image_id":8,"category_id":null},{"segmentation":[[1099,8,1173,8,1173,45,1099,45]],"area":2738,"bbox":[1099,8,74,37],"iscrowd":0,"id":263,"image_id":8,"category_id":null},{"segmentation":[[1181,7,1265,7,1265,46,1181,46]],"area":3276,"bbox":[1181,7,84,39],"iscrowd":0,"id":264,"image_id":8,"category_id":null},{"segmentation":[[968,72,1102,72,1102,105,968,105]],"area":4422,"bbox":[968,72,134,33],"iscrowd":0,"id":265,"image_id":8,"category_id":null},{"segmentation":[[1044,110,1102,110,1102,128,1044,128]],"area":1044,"bbox":[1044,110,58,18],"iscrowd":0,"id":266,"image_id":8,"category_id":null},{"segmentation":[[231,10,281,10,281,47,231,47]],"area":1850,"bbox":[231,10,50,37],"iscrowd":0,"id":267,"image_id":8,"category_id":null},{"segmentation":[[23,544,141,544,141,564,23,564]],"area":2360,"bbox":[23,544,118,20],"iscrowd":0,"id":268,"image_id":8,"category_id":null},{"segmentation":[[24,509,142,509,142,524,24,524]],"area":1770,"bbox":[24,509,118,15],"iscrowd":0,"id":269,"image_id":8,"category_id":null},{"segmentation":[[25,488,143,488,143,508,25,508]],"area":2360,"bbox":[25,488,118,20],"iscrowd":0,"id":270,"image_id":8,"category_id":null},{"segmentation":[[24,471,164,471,164,487,24,487]],"area":2240,"bbox":[24,471,140,16],"iscrowd":0,"id":271,"image_id":8,"category_id":null},{"segmentation":[[25,451,143,451,143,471,25,471]],"area":2360,"bbox":[25,451,118,20],"iscrowd":0,"id":272,"image_id":8,"category_id":null},{"segmentation":[[23,435,141,435,141,450,23,450]],"area":1770,"bbox":[23,435,118,15],"iscrowd":0,"id":273,"image_id":8,"category_id":null},{"segmentation":[[24,414,142,414,142,434,24,434]],"area":2360,"bbox":[24,414,118,20],"iscrowd":0,"id":274,"image_id":8,"category_id":null},{"segmentation":[[25,397,143,397,143,413,25,413]],"area":1888,"bbox":[25,397,118,16],"iscrowd":0,"id":275,"image_id":8,"category_id":null},{"segmentation":[[24,523,142,523,142,543,24,543]],"area":2360,"bbox":[24,523,118,20],"iscrowd":0,"id":276,"image_id":8,"category_id":null},{"segmentation":[[25,349,143,349,143,369,25,369]],"area":2360,"bbox":[25,349,118,20],"iscrowd":0,"id":277,"image_id":8,"category_id":null},{"segmentation":[[25,314,143,314,143,329,25,329]],"area":1770,"bbox":[25,314,118,15],"iscrowd":0,"id":278,"image_id":8,"category_id":null},{"segmentation":[[24,293,142,293,142,313,24,313]],"area":2360,"bbox":[24,293,118,20],"iscrowd":0,"id":279,"image_id":8,"category_id":null},{"segmentation":[[22,276,162,276,162,292,22,292]],"area":2240,"bbox":[22,276,140,16],"iscrowd":0,"id":280,"image_id":8,"category_id":null},{"segmentation":[[16,256,134,256,134,276,16,276]],"area":2360,"bbox":[16,256,118,20],"iscrowd":0,"id":281,"image_id":8,"category_id":null},{"segmentation":[[14,240,132,240,132,255,14,255]],"area":1770,"bbox":[14,240,118,15],"iscrowd":0,"id":282,"image_id":8,"category_id":null},{"segmentation":[[13,219,131,219,131,239,13,239]],"area":2360,"bbox":[13,219,118,20],"iscrowd":0,"id":283,"image_id":8,"category_id":null},{"segmentation":[[11,202,129,202,129,218,11,218]],"area":1888,"bbox":[11,202,118,16],"iscrowd":0,"id":284,"image_id":8,"category_id":null},{"segmentation":[[25,328,143,328,143,348,25,348]],"area":2360,"bbox":[25,328,118,20],"iscrowd":0,"id":285,"image_id":8,"category_id":null},{"segmentation":[[20,563,93,563,93,574,20,574]],"area":803,"bbox":[20,563,73,11],"iscrowd":0,"id":286,"image_id":8,"category_id":null},{"segmentation":[[22,609,193,609,193,627,22,627]],"area":3078,"bbox":[22,609,171,18],"iscrowd":0,"id":287,"image_id":8,"category_id":null},{"segmentation":[[26,631,173,631,173,645,26,645]],"area":2058,"bbox":[26,631,147,14],"iscrowd":0,"id":288,"image_id":8,"category_id":null},{"segmentation":[[24,650,80,650,80,662,24,662]],"area":672,"bbox":[24,650,56,12],"iscrowd":0,"id":289,"image_id":8,"category_id":null},{"segmentation":[[26,667,115,667,115,682,26,682]],"area":1335,"bbox":[26,667,89,15],"iscrowd":0,"id":290,"image_id":8,"category_id":null},{"segmentation":[[18,684,93,684,93,703,18,703]],"area":1425,"bbox":[18,684,75,19],"iscrowd":0,"id":291,"image_id":8,"category_id":null},{"segmentation":[[24,737,108,737,108,753,24,753]],"area":1344,"bbox":[24,737,84,16],"iscrowd":0,"id":292,"image_id":8,"category_id":null},{"segmentation":[[20,754,109,754,109,770,20,770]],"area":1424,"bbox":[20,754,89,16],"iscrowd":0,"id":293,"image_id":8,"category_id":null},{"segmentation":[[281,383,496,383,496,762,281,762]],"area":81485,"bbox":[281,383,215,379],"iscrowd":0,"id":294,"image_id":8,"category_id":null},{"segmentation":[[516,388,733,388,733,759,516,759]],"area":80507,"bbox":[516,388,217,371],"iscrowd":0,"id":295,"image_id":8,"category_id":null},{"segmentation":[[752,383,971,383,971,758,752,758]],"area":82125,"bbox":[752,383,219,375],"iscrowd":0,"id":296,"image_id":8,"category_id":null},{"segmentation":[[991,389,1212,389,1212,759,991,759]],"area":81770,"bbox":[991,389,221,370],"iscrowd":0,"id":297,"image_id":8,"category_id":null},{"segmentation":[[1224,522,1258,522,1258,559,1224,559]],"area":1258,"bbox":[1224,522,34,37],"iscrowd":0,"id":298,"image_id":8,"category_id":null},{"segmentation":[[233,521,266,521,266,560,233,560]],"area":1287,"bbox":[233,521,33,39],"iscrowd":0,"id":299,"image_id":8,"category_id":null},{"segmentation":[[871,321,967,321,967,359,871,359]],"area":3648,"bbox":[871,321,96,38],"iscrowd":0,"id":300,"image_id":8,"category_id":null},{"segmentation":[[751,320,865,320,865,358,751,358]],"area":4332,"bbox":[751,320,114,38],"iscrowd":0,"id":301,"image_id":8,"category_id":null},{"segmentation":[[984,320,1098,320,1098,358,984,358]],"area":4332,"bbox":[984,320,114,38],"iscrowd":0,"id":302,"image_id":8,"category_id":null},{"segmentation":[[511,321,607,321,607,359,511,359]],"area":3648,"bbox":[511,321,96,38],"iscrowd":0,"id":303,"image_id":8,"category_id":null},{"segmentation":[[391,320,505,320,505,358,391,358]],"area":4332,"bbox":[391,320,114,38],"iscrowd":0,"id":304,"image_id":8,"category_id":null},{"segmentation":[[624,320,738,320,738,358,624,358]],"area":4332,"bbox":[624,320,114,38],"iscrowd":0,"id":305,"image_id":8,"category_id":null},{"segmentation":[[285,100,414,100,414,140,285,140]],"area":5160,"bbox":[285,100,129,40],"iscrowd":0,"id":306,"image_id":8,"category_id":null},{"segmentation":[[417,101,550,101,550,140,417,140]],"area":5187,"bbox":[417,101,133,39],"iscrowd":0,"id":307,"image_id":8,"category_id":null},{"segmentation":[[551,102,630,102,630,141,551,141]],"area":3081,"bbox":[551,102,79,39],"iscrowd":0,"id":308,"image_id":8,"category_id":null},{"segmentation":[[632,101,729,101,729,146,632,146]],"area":4365,"bbox":[632,101,97,45],"iscrowd":0,"id":309,"image_id":8,"category_id":null},{"segmentation":[[733,103,876,103,876,139,733,139]],"area":5148,"bbox":[733,103,143,36],"iscrowd":0,"id":310,"image_id":8,"category_id":null},{"segmentation":[[1154,103,1264,103,1264,141,1154,141]],"area":4180,"bbox":[1154,103,110,38],"iscrowd":0,"id":311,"image_id":8,"category_id":null},{"segmentation":[[447,59,516,59,516,97,447,97]],"area":2622,"bbox":[447,59,69,38],"iscrowd":0,"id":312,"image_id":8,"category_id":null},{"segmentation":[[374,62,448,62,448,91,374,91]],"area":2146,"bbox":[374,62,74,29],"iscrowd":0,"id":313,"image_id":8,"category_id":null},{"segmentation":[[303,59,373,59,373,92,303,92]],"area":2310,"bbox":[303,59,70,33],"iscrowd":0,"id":314,"image_id":8,"category_id":null},{"segmentation":[[173,58,302,58,302,92,173,92]],"area":4386,"bbox":[173,58,129,34],"iscrowd":0,"id":315,"image_id":8,"category_id":null},{"segmentation":[[75,57,171,57,171,93,75,93]],"area":3456,"bbox":[75,57,96,36],"iscrowd":0,"id":316,"image_id":8,"category_id":null},{"segmentation":[[6,65,75,65,75,93,6,93]],"area":1932,"bbox":[6,65,69,28],"iscrowd":0,"id":317,"image_id":8,"category_id":null},{"segmentation":[[283,9,831,9,831,50,283,50]],"area":22468,"bbox":[283,9,548,41],"iscrowd":0,"id":318,"image_id":9,"category_id":null},{"segmentation":[[832,8,875,8,875,47,832,47]],"area":1677,"bbox":[832,8,43,39],"iscrowd":0,"id":319,"image_id":9,"category_id":null},{"segmentation":[[880,11,957,11,957,48,880,48]],"area":2849,"bbox":[880,11,77,37],"iscrowd":0,"id":320,"image_id":9,"category_id":null},{"segmentation":[[963,8,1091,8,1091,48,963,48]],"area":5120,"bbox":[963,8,128,40],"iscrowd":0,"id":321,"image_id":9,"category_id":null},{"segmentation":[[1099,8,1173,8,1173,45,1099,45]],"area":2738,"bbox":[1099,8,74,37],"iscrowd":0,"id":322,"image_id":9,"category_id":null},{"segmentation":[[1181,7,1265,7,1265,46,1181,46]],"area":3276,"bbox":[1181,7,84,39],"iscrowd":0,"id":323,"image_id":9,"category_id":null},{"segmentation":[[968,72,1102,72,1102,105,968,105]],"area":4422,"bbox":[968,72,134,33],"iscrowd":0,"id":324,"image_id":9,"category_id":null},{"segmentation":[[1044,110,1102,110,1102,128,1044,128]],"area":1044,"bbox":[1044,110,58,18],"iscrowd":0,"id":325,"image_id":9,"category_id":null},{"segmentation":[[231,10,281,10,281,47,231,47]],"area":1850,"bbox":[231,10,50,37],"iscrowd":0,"id":326,"image_id":9,"category_id":null},{"segmentation":[[23,220,162,220,162,242,23,242]],"area":3058,"bbox":[23,220,139,22],"iscrowd":0,"id":327,"image_id":9,"category_id":null},{"segmentation":[[25,187,109,187,109,209,25,209]],"area":1848,"bbox":[25,187,84,22],"iscrowd":0,"id":328,"image_id":9,"category_id":null},{"segmentation":[[26,204,165,204,165,226,26,226]],"area":3058,"bbox":[26,204,139,22],"iscrowd":0,"id":329,"image_id":9,"category_id":null},{"segmentation":[[24,165,163,165,163,187,24,187]],"area":3058,"bbox":[24,165,139,22],"iscrowd":0,"id":330,"image_id":9,"category_id":null},{"segmentation":[[26,112,110,112,110,134,26,134]],"area":1848,"bbox":[26,112,84,22],"iscrowd":0,"id":331,"image_id":9,"category_id":null},{"segmentation":[[27,139,166,139,166,161,27,161]],"area":3058,"bbox":[27,139,139,22],"iscrowd":0,"id":332,"image_id":9,"category_id":null},{"segmentation":[[19,632,200,632,200,649,19,649]],"area":3077,"bbox":[19,632,181,17],"iscrowd":0,"id":333,"image_id":9,"category_id":null},{"segmentation":[[22,653,161,653,161,670,22,670]],"area":2363,"bbox":[22,653,139,17],"iscrowd":0,"id":334,"image_id":9,"category_id":null},{"segmentation":[[20,584,159,584,159,601,20,601]],"area":2363,"bbox":[20,584,139,17],"iscrowd":0,"id":335,"image_id":9,"category_id":null},{"segmentation":[[16,561,155,561,155,578,16,578]],"area":2363,"bbox":[16,561,139,17],"iscrowd":0,"id":336,"image_id":9,"category_id":null},{"segmentation":[[23,240,162,240,162,257,23,257]],"area":2363,"bbox":[23,240,139,17],"iscrowd":0,"id":337,"image_id":9,"category_id":null},{"segmentation":[[14,535,153,535,153,552,14,552]],"area":2363,"bbox":[14,535,139,17],"iscrowd":0,"id":338,"image_id":9,"category_id":null},{"segmentation":[[24,329,163,329,163,346,24,346]],"area":2363,"bbox":[24,329,139,17],"iscrowd":0,"id":339,"image_id":9,"category_id":null},{"segmentation":[[27,294,166,294,166,311,27,311]],"area":2363,"bbox":[27,294,139,17],"iscrowd":0,"id":340,"image_id":9,"category_id":null},{"segmentation":[[27,313,166,313,166,330,27,330]],"area":2363,"bbox":[27,313,139,17],"iscrowd":0,"id":341,"image_id":9,"category_id":null},{"segmentation":[[20,275,159,275,159,292,20,292]],"area":2363,"bbox":[20,275,139,17],"iscrowd":0,"id":342,"image_id":9,"category_id":null},{"segmentation":[[23,259,162,259,162,276,23,276]],"area":2363,"bbox":[23,259,139,17],"iscrowd":0,"id":343,"image_id":9,"category_id":null},{"segmentation":[[12,605,151,605,151,622,12,622]],"area":2363,"bbox":[12,605,139,17],"iscrowd":0,"id":344,"image_id":9,"category_id":null},{"segmentation":[[24,439,163,439,163,456,24,456]],"area":2363,"bbox":[24,439,139,17],"iscrowd":0,"id":345,"image_id":9,"category_id":null},{"segmentation":[[28,386,167,386,167,403,28,403]],"area":2363,"bbox":[28,386,139,17],"iscrowd":0,"id":346,"image_id":9,"category_id":null},{"segmentation":[[28,405,167,405,167,422,28,422]],"area":2363,"bbox":[28,405,139,17],"iscrowd":0,"id":347,"image_id":9,"category_id":null},{"segmentation":[[21,367,160,367,160,384,21,384]],"area":2363,"bbox":[21,367,139,17],"iscrowd":0,"id":348,"image_id":9,"category_id":null},{"segmentation":[[24,351,163,351,163,368,24,368]],"area":2363,"bbox":[24,351,139,17],"iscrowd":0,"id":349,"image_id":9,"category_id":null},{"segmentation":[[25,421,164,421,164,438,25,438]],"area":2363,"bbox":[25,421,139,17],"iscrowd":0,"id":350,"image_id":9,"category_id":null},{"segmentation":[[59,558,63,558,63,566,59,566]],"area":32,"bbox":[59,558,4,8],"iscrowd":0,"id":351,"image_id":9,"category_id":null},{"segmentation":[[239,489,557,489,557,792,239,792]],"area":96354,"bbox":[239,489,318,303],"iscrowd":0,"id":352,"image_id":9,"category_id":null},{"segmentation":[[921,483,1272,483,1272,793,921,793]],"area":108810,"bbox":[921,483,351,310],"iscrowd":0,"id":353,"image_id":9,"category_id":null},{"segmentation":[[566,486,917,486,917,796,566,796]],"area":108810,"bbox":[566,486,351,310],"iscrowd":0,"id":354,"image_id":9,"category_id":null},{"segmentation":[[383,9,831,9,831,50,383,50]],"area":18368,"bbox":[383,9,448,41],"iscrowd":0,"id":355,"image_id":10,"category_id":null},{"segmentation":[[832,8,875,8,875,47,832,47]],"area":1677,"bbox":[832,8,43,39],"iscrowd":0,"id":356,"image_id":10,"category_id":null},{"segmentation":[[880,11,957,11,957,48,880,48]],"area":2849,"bbox":[880,11,77,37],"iscrowd":0,"id":357,"image_id":10,"category_id":null},{"segmentation":[[963,8,1091,8,1091,48,963,48]],"area":5120,"bbox":[963,8,128,40],"iscrowd":0,"id":358,"image_id":10,"category_id":null},{"segmentation":[[1099,8,1173,8,1173,45,1099,45]],"area":2738,"bbox":[1099,8,74,37],"iscrowd":0,"id":359,"image_id":10,"category_id":null},{"segmentation":[[1181,7,1265,7,1265,46,1181,46]],"area":3276,"bbox":[1181,7,84,39],"iscrowd":0,"id":360,"image_id":10,"category_id":null},{"segmentation":[[348,128,411,128,411,157,348,157]],"area":1827,"bbox":[348,128,63,29],"iscrowd":0,"id":361,"image_id":10,"category_id":null},{"segmentation":[[428,127,548,127,548,156,428,156]],"area":3480,"bbox":[428,127,120,29],"iscrowd":0,"id":362,"image_id":10,"category_id":null},{"segmentation":[[968,72,1102,72,1102,105,968,105]],"area":4422,"bbox":[968,72,134,33],"iscrowd":0,"id":363,"image_id":10,"category_id":null},{"segmentation":[[1044,110,1102,110,1102,128,1044,128]],"area":1044,"bbox":[1044,110,58,18],"iscrowd":0,"id":364,"image_id":10,"category_id":null},{"segmentation":[[231,10,382,10,382,47,231,47]],"area":5587,"bbox":[231,10,151,37],"iscrowd":0,"id":365,"image_id":10,"category_id":null},{"segmentation":[[1039,362,1231,362,1231,734,1039,734]],"area":71424,"bbox":[1039,362,192,372],"iscrowd":0,"id":366,"image_id":10,"category_id":null},{"segmentation":[[273,369,465,369,465,741,273,741]],"area":71424,"bbox":[273,369,192,372],"iscrowd":0,"id":367,"image_id":10,"category_id":null},{"segmentation":[[843,365,1035,365,1035,737,843,737]],"area":71424,"bbox":[843,365,192,372],"iscrowd":0,"id":368,"image_id":10,"category_id":null},{"segmentation":[[664,366,835,366,835,738,664,738]],"area":63612,"bbox":[664,366,171,372],"iscrowd":0,"id":369,"image_id":10,"category_id":null},{"segmentation":[[468,369,660,369,660,741,468,741]],"area":71424,"bbox":[468,369,192,372],"iscrowd":0,"id":370,"image_id":10,"category_id":null},{"segmentation":[[13,252,134,252,134,270,13,270]],"area":2178,"bbox":[13,252,121,18],"iscrowd":0,"id":371,"image_id":10,"category_id":null},{"segmentation":[[20,273,131,273,131,291,20,291]],"area":1998,"bbox":[20,273,111,18],"iscrowd":0,"id":372,"image_id":10,"category_id":null},{"segmentation":[[26,297,172,297,172,306,26,306]],"area":1314,"bbox":[26,297,146,9],"iscrowd":0,"id":373,"image_id":10,"category_id":null},{"segmentation":[[27,313,114,313,114,327,27,327]],"area":1218,"bbox":[27,313,87,14],"iscrowd":0,"id":374,"image_id":10,"category_id":null},{"segmentation":[[26,333,187,333,187,346,26,346]],"area":2093,"bbox":[26,333,161,13],"iscrowd":0,"id":375,"image_id":10,"category_id":null},{"segmentation":[[24,351,153,351,153,365,24,365]],"area":1806,"bbox":[24,351,129,14],"iscrowd":0,"id":376,"image_id":10,"category_id":null},{"segmentation":[[24,371,98,371,98,380,24,380]],"area":666,"bbox":[24,371,74,9],"iscrowd":0,"id":377,"image_id":10,"category_id":null},{"segmentation":[[24,386,136,386,136,402,24,402]],"area":1792,"bbox":[24,386,112,16],"iscrowd":0,"id":378,"image_id":10,"category_id":null},{"segmentation":[[24,403,151,403,151,418,24,418]],"area":1905,"bbox":[24,403,127,15],"iscrowd":0,"id":379,"image_id":10,"category_id":null},{"segmentation":[[24,423,156,423,156,435,24,435]],"area":1584,"bbox":[24,423,132,12],"iscrowd":0,"id":380,"image_id":10,"category_id":null},{"segmentation":[[22,441,88,441,88,453,22,453]],"area":792,"bbox":[22,441,66,12],"iscrowd":0,"id":381,"image_id":10,"category_id":null},{"segmentation":[[27,491,191,491,191,505,27,505]],"area":2296,"bbox":[27,491,164,14],"iscrowd":0,"id":382,"image_id":10,"category_id":null},{"segmentation":[[26,510,171,510,171,521,26,521]],"area":1595,"bbox":[26,510,145,11],"iscrowd":0,"id":383,"image_id":10,"category_id":null},{"segmentation":[[31,529,74,529,74,542,31,542]],"area":559,"bbox":[31,529,43,13],"iscrowd":0,"id":384,"image_id":10,"category_id":null},{"segmentation":[[26,547,123,547,123,565,26,565]],"area":1746,"bbox":[26,547,97,18],"iscrowd":0,"id":385,"image_id":10,"category_id":null},{"segmentation":[[22,595,129,595,129,611,22,611]],"area":1712,"bbox":[22,595,107,16],"iscrowd":0,"id":386,"image_id":10,"category_id":null},{"segmentation":[[23,613,110,613,110,633,23,633]],"area":1740,"bbox":[23,613,87,20],"iscrowd":0,"id":387,"image_id":10,"category_id":null},{"segmentation":[[24,689,102,689,102,711,24,711]],"area":1716,"bbox":[24,689,78,22],"iscrowd":0,"id":388,"image_id":10,"category_id":null},{"segmentation":[[24,714,198,714,198,732,24,732]],"area":3132,"bbox":[24,714,174,18],"iscrowd":0,"id":389,"image_id":10,"category_id":null},{"segmentation":[[24,736,130,736,130,754,24,754]],"area":1908,"bbox":[24,736,106,18],"iscrowd":0,"id":390,"image_id":10,"category_id":null},{"segmentation":[[28,760,129,760,129,780,28,780]],"area":2020,"bbox":[28,760,101,20],"iscrowd":0,"id":391,"image_id":10,"category_id":null},{"segmentation":[[26,786,129,786,129,800,26,800]],"area":1442,"bbox":[26,786,103,14],"iscrowd":0,"id":392,"image_id":10,"category_id":null},{"segmentation":[[234,516,270,516,270,566,234,566]],"area":1800,"bbox":[234,516,36,50],"iscrowd":0,"id":393,"image_id":10,"category_id":null},{"segmentation":[[1229,525,1251,525,1251,561,1229,561]],"area":792,"bbox":[1229,525,22,36],"iscrowd":0,"id":394,"image_id":10,"category_id":null},{"segmentation":[[11,64,65,64,65,92,11,92]],"area":1512,"bbox":[11,64,54,28],"iscrowd":0,"id":395,"image_id":10,"category_id":null}],"licenses":[{"id":0,"name":"Unknown License","url":""}],"categories":[{"supercategory":"type","id":null,"name":"Human"},{"supercategory":"type","id":null,"name":"search Bar"},{"supercategory":"type","id":null,"name":"Button"},{"supercategory":"type","id":null,"name":""}]}